basex64/__init__.py
basex64/basex64.py
basex64-0.0.1.250102.dist-info/LICENSE.txt
basex64-0.0.1.250102.dist-info/WHEEL
basex64-0.0.1.250102.dist-info/METADATA
basex64-0.0.1.250102.dist-info/RECORD
