Metadata-Version: 2.3
Name: basex64
Version: 0.0.1.250102
Summary: BaseX64: A simple cryptographic tool for storing data in distributed version control systems like Git.
Home-page: https://github.com/codyverse/basex64
License: MIT
Keywords: cipher, cryptography, encryption, base64, git
Author: Andrii Burkatskyi aka andr11b
Author-email: 4ndr116@gmail.com
Requires-Python: >=3.8
